[
    {
        "id": 1023,
        "name": "Admira Wacker",
        "code": "ADM",
        "country": "Austria",
        "founded": 2008,
        "national": false,
        "logo": "https://media.api-sports.io/football/teams/1023.png",
        "venue_id": 20412
    },
    {
        "id": 1027,
        "name": "SKN ST. Polten",
        "code": "POL",
        "country": "Austria",
        "founded": 2000,
        "national": false,
        "logo": "https://media.api-sports.io/football/teams/1027.png",
        "venue_id": 149
    },
    {
        "id": 1028,
        "name": "Ried",
        "code": "RIE",
        "country": "Austria",
        "founded": 1912,
        "national": false,
        "logo": "https://media.api-sports.io/football/teams/1028.png",
        "venue_id": 19921
    },
    {
        "id": 1395,
        "name": "Floridsdorfer AC",
        "code": "TEA",
        "country": "Austria",
        "founded": 1904,
        "national": false,
        "logo": "https://media.api-sports.io/football/teams/1395.png",
        "venue_id": 19920
    },
    {
        "id": 1397,
        "name": "SV Horn",
        "code": "HOR",
        "country": "Austria",
        "founded": 1922,
        "national": false,
        "logo": "https://media.api-sports.io/football/teams/1397.png",
        "venue_id": 10507
    },
    {
        "id": 1399,
        "name": "Austria Lustenau",
        "code": "LUS",
        "country": "Austria",
        "founded": 1914,
        "national": false,
        "logo": "https://media.api-sports.io/football/teams/1399.png",
        "venue_id": 10523
    },
    {
        "id": 1400,
        "name": "FC Liefering",
        "code": "LIE",
        "country": "Austria",
        "founded": 1947,
        "national": false,
        "logo": "https://media.api-sports.io/football/teams/1400.png",
        "venue_id": 148
    },
    {
        "id": 1401,
        "name": "SV Kapfenberg",
        "code": "KAP",
        "country": "Austria",
        "founded": 1919,
        "national": false,
        "logo": "https://media.api-sports.io/football/teams/1401.png",
        "venue_id": 19512
    },
    {
        "id": 1402,
        "name": "SV Lafnitz",
        "code": "LAF",
        "country": "Austria",
        "founded": null,
        "national": false,
        "logo": "https://media.api-sports.io/football/teams/1402.png",
        "venue_id": 1725
    },
    {
        "id": 1404,
        "name": "SKU Amstetten",
        "code": "AMS",
        "country": "Austria",
        "founded": null,
        "national": false,
        "logo": "https://media.api-sports.io/football/teams/1404.png",
        "venue_id": 133
    },
    {
        "id": 4990,
        "name": "First Vienna",
        "code": "FIR",
        "country": "Austria",
        "founded": 1894,
        "national": false,
        "logo": "https://media.api-sports.io/football/teams/4990.png",
        "venue_id": 19947
    },
    {
        "id": 4993,
        "name": "Stripfing",
        "code": null,
        "country": "Austria",
        "founded": null,
        "national": false,
        "logo": "https://media.api-sports.io/football/teams/4993.png",
        "venue_id": 19920
    },
    {
        "id": 8247,
        "name": "Rapid Wien II",
        "code": "RAP",
        "country": "Austria",
        "founded": 1898,
        "national": false,
        "logo": "https://media.api-sports.io/football/teams/8247.png",
        "venue_id": 19958
    },
    {
        "id": 8251,
        "name": "Sturm Graz II",
        "code": "STU",
        "country": "Austria",
        "founded": 1909,
        "national": false,
        "logo": "https://media.api-sports.io/football/teams/8251.png",
        "venue_id": 3733
    },
    {
        "id": 8259,
        "name": "Schwarz-Weiß Bregenz",
        "code": "BRE",
        "country": "Austria",
        "founded": 2005,
        "national": false,
        "logo": "https://media.api-sports.io/football/teams/8259.png",
        "venue_id": 10523
    },
    {
        "id": 8332,
        "name": "Voitsberg",
        "code": null,
        "country": "Austria",
        "founded": 1921,
        "national": false,
        "logo": "https://media.api-sports.io/football/teams/8332.png",
        "venue_id": 19961
    },
    {
        "id": 571,
        "name": "Red Bull Salzburg",
        "code": "SAL",
        "country": "Austria",
        "founded": 1933,
        "national": false,
        "logo": "https://media.api-sports.io/football/teams/571.png",
        "venue_id": 148
    },
    {
        "id": 601,
        "name": "Austria Vienna",
        "code": "AUS",
        "country": "Austria",
        "founded": 1911,
        "national": false,
        "logo": "https://media.api-sports.io/football/teams/601.png",
        "venue_id": 136
    },
    {
        "id": 618,
        "name": "SCR Altach",
        "code": "ALT",
        "country": "Austria",
        "founded": 1929,
        "national": false,
        "logo": "https://media.api-sports.io/football/teams/618.png",
        "venue_id": 146
    },
    {
        "id": 637,
        "name": "Sturm Graz",
        "code": "STU",
        "country": "Austria",
        "founded": 1909,
        "national": false,
        "logo": "https://media.api-sports.io/football/teams/637.png",
        "venue_id": 150
    },
    {
        "id": 781,
        "name": "Rapid Vienna",
        "code": "RAP",
        "country": "Austria",
        "founded": 1899,
        "national": false,
        "logo": "https://media.api-sports.io/football/teams/781.png",
        "venue_id": 145
    },
    {
        "id": 1025,
        "name": "Wolfsberger AC",
        "code": "WOL",
        "country": "Austria",
        "founded": 1931,
        "national": false,
        "logo": "https://media.api-sports.io/football/teams/1025.png",
        "venue_id": 1761
    },
    {
        "id": 1026,
        "name": "Lask Linz",
        "code": "LAS",
        "country": "Austria",
        "founded": 1908,
        "national": false,
        "logo": "https://media.api-sports.io/football/teams/1026.png",
        "venue_id": 143
    },
    {
        "id": 1072,
        "name": "TSV Hartberg",
        "code": "HAR",
        "country": "Austria",
        "founded": 1946,
        "national": false,
        "logo": "https://media.api-sports.io/football/teams/1072.png",
        "venue_id": 140
    },
    {
        "id": 1394,
        "name": "FC BW Linz",
        "code": "LIN",
        "country": "Austria",
        "founded": 1997,
        "national": false,
        "logo": "https://media.api-sports.io/football/teams/1394.png",
        "venue_id": 11873
    },
    {
        "id": 1398,
        "name": "WSG Wattens",
        "code": "WAT",
        "country": "Austria",
        "founded": 1930,
        "national": false,
        "logo": "https://media.api-sports.io/football/teams/1398.png",
        "venue_id": 152
    },
    {
        "id": 1405,
        "name": "Austria Klagenfurt",
        "code": null,
        "country": "Austria",
        "founded": null,
        "national": false,
        "logo": "https://media.api-sports.io/football/teams/1405.png",
        "venue_id": 11874
    },
    {
        "id": 4256,
        "name": "Grazer AK",
        "code": null,
        "country": "Austria",
        "founded": 1902,
        "national": false,
        "logo": "https://media.api-sports.io/football/teams/4256.png",
        "venue_id": 150
    },
    {
        "id": 4255,
        "name": "Dornbirn",
        "code": "DOR",
        "country": "Austria",
        "founded": 1913,
        "national": false,
        "logo": "https://media.api-sports.io/football/teams/4255.png",
        "venue_id": 20339
    },
    {
        "id": 4937,
        "name": "Draßburg",
        "code": null,
        "country": "Austria",
        "founded": null,
        "national": false,
        "logo": "https://media.api-sports.io/football/teams/4937.png",
        "venue_id": 3730
    },
    {
        "id": 4941,
        "name": "Gloggnitz",
        "code": null,
        "country": "Austria",
        "founded": 1922,
        "national": false,
        "logo": "https://media.api-sports.io/football/teams/4941.png",
        "venue_id": 19403
    },
    {
        "id": 4942,
        "name": "Gurten",
        "code": null,
        "country": "Austria",
        "founded": null,
        "national": false,
        "logo": "https://media.api-sports.io/football/teams/4942.png",
        "venue_id": 3734
    },
    {
        "id": 4945,
        "name": "Hohenems",
        "code": null,
        "country": "Austria",
        "founded": 1923,
        "national": false,
        "logo": "https://media.api-sports.io/football/teams/4945.png",
        "venue_id": 3737
    },
    {
        "id": 4947,
        "name": "Kitzbühel",
        "code": null,
        "country": "Austria",
        "founded": null,
        "national": false,
        "logo": "https://media.api-sports.io/football/teams/4947.png",
        "venue_id": 3739
    },
    {
        "id": 4949,
        "name": "Köttmannsdorf",
        "code": null,
        "country": "Austria",
        "founded": null,
        "national": false,
        "logo": "https://media.api-sports.io/football/teams/4949.png",
        "venue_id": 3741
    },
    {
        "id": 4951,
        "name": "Leobendorf",
        "code": null,
        "country": "Austria",
        "founded": null,
        "national": false,
        "logo": "https://media.api-sports.io/football/teams/4951.png",
        "venue_id": 3743
    },
    {
        "id": 4952,
        "name": "Mannsdorf-Großenzersdorf",
        "code": "MAN",
        "country": "Austria",
        "founded": 1985,
        "national": false,
        "logo": "https://media.api-sports.io/football/teams/4952.png",
        "venue_id": 3744
    },
    {
        "id": 4954,
        "name": "Neusiedl",
        "code": null,
        "country": "Austria",
        "founded": 1919,
        "national": false,
        "logo": "https://media.api-sports.io/football/teams/4954.png",
        "venue_id": 3746
    },
    {
        "id": 4957,
        "name": "Schwaz",
        "code": "SCH",
        "country": "Austria",
        "founded": 1921,
        "national": false,
        "logo": "https://media.api-sports.io/football/teams/4957.png",
        "venue_id": 3749
    },
    {
        "id": 4959,
        "name": "St. Anna",
        "code": null,
        "country": "Austria",
        "founded": 1974,
        "national": false,
        "logo": "https://media.api-sports.io/football/teams/4959.png",
        "venue_id": 3751
    },
    {
        "id": 4961,
        "name": "Traiskirchen",
        "code": null,
        "country": "Austria",
        "founded": 1927,
        "national": false,
        "logo": "https://media.api-sports.io/football/teams/4961.png",
        "venue_id": 19578
    },
    {
        "id": 4962,
        "name": "Treibach",
        "code": null,
        "country": "Austria",
        "founded": null,
        "national": false,
        "logo": "https://media.api-sports.io/football/teams/4962.png",
        "venue_id": 3754
    },
    {
        "id": 4966,
        "name": "Wiener Viktoria",
        "code": "WIE",
        "country": "Austria",
        "founded": 1931,
        "national": false,
        "logo": "https://media.api-sports.io/football/teams/4966.png",
        "venue_id": 3758
    },
    {
        "id": 4972,
        "name": "Deutschlandsberger SC",
        "code": null,
        "country": "Austria",
        "founded": null,
        "national": false,
        "logo": "https://media.api-sports.io/football/teams/4972.png",
        "venue_id": 3764
    },
    {
        "id": 4979,
        "name": "Oedt",
        "code": null,
        "country": "Austria",
        "founded": null,
        "national": false,
        "logo": "https://media.api-sports.io/football/teams/4979.png",
        "venue_id": 3770
    },
    {
        "id": 4980,
        "name": "Pinzgau Saalfelden",
        "code": null,
        "country": "Austria",
        "founded": null,
        "national": false,
        "logo": "https://media.api-sports.io/football/teams/4980.png",
        "venue_id": 19946
    },
    {
        "id": 4981,
        "name": "SVG Reichenau",
        "code": null,
        "country": "Austria",
        "founded": null,
        "national": false,
        "logo": "https://media.api-sports.io/football/teams/4981.png",
        "venue_id": 3772
    },
    {
        "id": 4983,
        "name": "Siegendorf",
        "code": null,
        "country": "Austria",
        "founded": 1930,
        "national": false,
        "logo": "https://media.api-sports.io/football/teams/4983.png",
        "venue_id": 20518
    },
    {
        "id": 4996,
        "name": "Weiz",
        "code": null,
        "country": "Austria",
        "founded": 1924,
        "national": false,
        "logo": "https://media.api-sports.io/football/teams/4996.png",
        "venue_id": 3787
    },
    {
        "id": 5000,
        "name": "Austria Salzburg",
        "code": "AUS",
        "country": "Austria",
        "founded": 2005,
        "national": false,
        "logo": "https://media.api-sports.io/football/teams/5000.png",
        "venue_id": 3792
    },
    {
        "id": 8258,
        "name": "Röthis",
        "code": null,
        "country": "Austria",
        "founded": null,
        "national": false,
        "logo": "https://media.api-sports.io/football/teams/8258.png",
        "venue_id": 5845
    },
    {
        "id": 8260,
        "name": "Bischofshofen",
        "code": null,
        "country": "Austria",
        "founded": null,
        "national": false,
        "logo": "https://media.api-sports.io/football/teams/8260.png",
        "venue_id": 5846
    },
    {
        "id": 8261,
        "name": "Wals-Grünau",
        "code": "WAL",
        "country": "Austria",
        "founded": 1957,
        "national": false,
        "logo": "https://media.api-sports.io/football/teams/8261.png",
        "venue_id": 5847
    },
    {
        "id": 8326,
        "name": "Leoben",
        "code": null,
        "country": "Austria",
        "founded": 1928,
        "national": false,
        "logo": "https://media.api-sports.io/football/teams/8326.png",
        "venue_id": 19960
    },
    {
        "id": 8333,
        "name": "Wildon",
        "code": null,
        "country": "Austria",
        "founded": null,
        "national": false,
        "logo": "https://media.api-sports.io/football/teams/8333.png",
        "venue_id": 5916
    },
    {
        "id": 8365,
        "name": "Donau",
        "code": null,
        "country": "Austria",
        "founded": null,
        "national": false,
        "logo": "https://media.api-sports.io/football/teams/8365.png",
        "venue_id": 5947
    },
    {
        "id": 8366,
        "name": "Fach-Donaufeld",
        "code": null,
        "country": "Austria",
        "founded": 1912,
        "national": false,
        "logo": "https://media.api-sports.io/football/teams/8366.png",
        "venue_id": 5948
    },
    {
        "id": 8372,
        "name": "Union Mauer",
        "code": null,
        "country": "Austria",
        "founded": null,
        "national": false,
        "logo": "https://media.api-sports.io/football/teams/8372.png",
        "venue_id": 5954
    },
    {
        "id": 11200,
        "name": "Oberwart",
        "code": "OBE",
        "country": "Austria",
        "founded": null,
        "national": false,
        "logo": "https://media.api-sports.io/football/teams/11200.png",
        "venue_id": 5857
    },
    {
        "id": 14709,
        "name": "Imst",
        "code": null,
        "country": "Austria",
        "founded": null,
        "national": false,
        "logo": "https://media.api-sports.io/football/teams/14709.png",
        "venue_id": 10722
    },
    {
        "id": 17197,
        "name": "ASK Klagenfurt",
        "code": null,
        "country": "Austria",
        "founded": null,
        "national": false,
        "logo": "https://media.api-sports.io/football/teams/17197.png",
        "venue_id": 12080
    },
    {
        "id": 19193,
        "name": "Wohnbau Dietach",
        "code": null,
        "country": "Austria",
        "founded": null,
        "national": false,
        "logo": "https://media.api-sports.io/football/teams/19193.png",
        "venue_id": 19867
    },
    {
        "id": 21390,
        "name": "Velden",
        "code": null,
        "country": "Austria",
        "founded": null,
        "national": false,
        "logo": "https://media.api-sports.io/football/teams/21390.png",
        "venue_id": 19986
    },
    {
        "id": 21534,
        "name": "Wallern / Marienkirchen",
        "code": null,
        "country": "Austria",
        "founded": null,
        "national": false,
        "logo": "https://media.api-sports.io/football/teams/21534.png",
        "venue_id": 5886
    },
    {
        "id": 21721,
        "name": "Korneuburg",
        "code": null,
        "country": "Austria",
        "founded": null,
        "national": false,
        "logo": "https://media.api-sports.io/football/teams/21721.png",
        "venue_id": 20202
    },
    {
        "id": 22213,
        "name": "WSPG Wels",
        "code": null,
        "country": "Austria",
        "founded": 2023,
        "national": false,
        "logo": "https://media.api-sports.io/football/teams/22213.png",
        "venue_id": 66559988989898
    },
    {
        "id": 19165,
        "name": "Kleinmünchen / BW Linz",
        "code": null,
        "country": "Austria",
        "founded": null,
        "national": false,
        "logo": "https://media.api-sports.io/football/teams/19165.png",
        "venue_id": 22060
    },
    {
        "id": 24440,
        "name": "LASK",
        "code": null,
        "country": "Austria",
        "founded": null,
        "national": false,
        "logo": "https://media.api-sports.io/football/teams/24440.png",
        "venue_id": 19623
    },
    {
        "id": 24441,
        "name": "Rheindorf Altach",
        "code": null,
        "country": "Austria",
        "founded": null,
        "national": false,
        "logo": "https://media.api-sports.io/football/teams/24441.png",
        "venue_id": 146
    },
    {
        "id": 4955,
        "name": "Parndorf",
        "code": "PAR",
        "country": "Austria",
        "founded": 1919,
        "national": false,
        "logo": "https://media.api-sports.io/football/teams/4955.png",
        "venue_id": 3747
    },
    {
        "id": 4956,
        "name": "Pinkafeld",
        "code": "PIN",
        "country": "Austria",
        "founded": null,
        "national": false,
        "logo": "https://media.api-sports.io/football/teams/4956.png",
        "venue_id": 3748
    },
    {
        "id": 4988,
        "name": "Bad Sauerbrunn",
        "code": null,
        "country": "Austria",
        "founded": null,
        "national": false,
        "logo": "https://media.api-sports.io/football/teams/4988.png",
        "venue_id": 3779
    },
    {
        "id": 8262,
        "name": "Deutschkreutz",
        "code": null,
        "country": "Austria",
        "founded": null,
        "national": false,
        "logo": "https://media.api-sports.io/football/teams/8262.png",
        "venue_id": 5848
    },
    {
        "id": 8265,
        "name": "Horitschon",
        "code": null,
        "country": "Austria",
        "founded": null,
        "national": false,
        "logo": "https://media.api-sports.io/football/teams/8265.png",
        "venue_id": 5851
    },
    {
        "id": 8266,
        "name": "Klingenbach",
        "code": null,
        "country": "Austria",
        "founded": null,
        "national": false,
        "logo": "https://media.api-sports.io/football/teams/8266.png",
        "venue_id": 18678
    },
    {
        "id": 8267,
        "name": "Kohfidisch",
        "code": null,
        "country": "Austria",
        "founded": null,
        "national": false,
        "logo": "https://media.api-sports.io/football/teams/8267.png",
        "venue_id": 5853
    },
    {
        "id": 8268,
        "name": "Leithaprodersdorf",
        "code": null,
        "country": "Austria",
        "founded": null,
        "national": false,
        "logo": "https://media.api-sports.io/football/teams/8268.png",
        "venue_id": 5854
    },
    {
        "id": 8272,
        "name": "St. Margarethen / Bur",
        "code": null,
        "country": "Austria",
        "founded": null,
        "national": false,
        "logo": "https://media.api-sports.io/football/teams/8272.png",
        "venue_id": 5858
    },
    {
        "id": 18388,
        "name": "Schattendorf",
        "code": null,
        "country": "Austria",
        "founded": null,
        "national": false,
        "logo": "https://media.api-sports.io/football/teams/18388.png",
        "venue_id": 12735
    },
    {
        "id": 19684,
        "name": "Jennersdorf",
        "code": null,
        "country": "Austria",
        "founded": null,
        "national": false,
        "logo": "https://media.api-sports.io/football/teams/19684.png",
        "venue_id": 21003
    },
    {
        "id": 21724,
        "name": "Edelserpentin",
        "code": null,
        "country": "Austria",
        "founded": null,
        "national": false,
        "logo": "https://media.api-sports.io/football/teams/21724.png",
        "venue_id": 21004
    },
    {
        "id": 21725,
        "name": "Halbturn",
        "code": null,
        "country": "Austria",
        "founded": null,
        "national": false,
        "logo": "https://media.api-sports.io/football/teams/21725.png",
        "venue_id": 20501
    },
    {
        "id": 24463,
        "name": "Mattersburg 2020",
        "code": null,
        "country": "Austria",
        "founded": 2020,
        "national": false,
        "logo": "https://media.api-sports.io/football/teams/24463.png",
        "venue_id": 144
    },
    {
        "id": 24464,
        "name": "SK Pama",
        "code": null,
        "country": "Austria",
        "founded": null,
        "national": false,
        "logo": "https://media.api-sports.io/football/teams/24464.png",
        "venue_id": 22502
    },
    {
        "id": 4967,
        "name": "Wolfsberg",
        "code": null,
        "country": "Austria",
        "founded": null,
        "national": false,
        "logo": "https://media.api-sports.io/football/teams/4967.png",
        "venue_id": 3759
    },
    {
        "id": 4975,
        "name": "Lendorf",
        "code": null,
        "country": "Austria",
        "founded": null,
        "national": false,
        "logo": "https://media.api-sports.io/football/teams/4975.png",
        "venue_id": 3766
    },
    {
        "id": 4987,
        "name": "Völkermarkt",
        "code": null,
        "country": "Austria",
        "founded": null,
        "national": false,
        "logo": "https://media.api-sports.io/football/teams/4987.png",
        "venue_id": 3778
    },
    {
        "id": 4989,
        "name": "Ferlach",
        "code": null,
        "country": "Austria",
        "founded": null,
        "national": false,
        "logo": "https://media.api-sports.io/football/teams/4989.png",
        "venue_id": 3780
    },
    {
        "id": 8273,
        "name": "Bleiburg",
        "code": null,
        "country": "Austria",
        "founded": null,
        "national": false,
        "logo": "https://media.api-sports.io/football/teams/8273.png",
        "venue_id": 5859
    },
    {
        "id": 8274,
        "name": "Dellach im Gailtal",
        "code": null,
        "country": "Austria",
        "founded": null,
        "national": false,
        "logo": "https://media.api-sports.io/football/teams/8274.png",
        "venue_id": 5860
    },
    {
        "id": 8278,
        "name": "Spittal",
        "code": null,
        "country": "Austria",
        "founded": null,
        "national": false,
        "logo": "https://media.api-sports.io/football/teams/8278.png",
        "venue_id": 5864
    },
    {
        "id": 8279,
        "name": "St. Jakob Rosental",
        "code": null,
        "country": "Austria",
        "founded": 1970,
        "national": false,
        "logo": "https://media.api-sports.io/football/teams/8279.png",
        "venue_id": 5865
    },
    {
        "id": 11209,
        "name": "St. Veit / Glan",
        "code": null,
        "country": "Austria",
        "founded": 1989,
        "national": false,
        "logo": "https://media.api-sports.io/football/teams/11209.png",
        "venue_id": 7489
    },
    {
        "id": 17207,
        "name": "SAK Klagenfurt",
        "code": "KLA",
        "country": "Austria",
        "founded": 1970,
        "national": false,
        "logo": "https://media.api-sports.io/football/teams/17207.png",
        "venue_id": 3790
    },
    {
        "id": 17208,
        "name": "KAC",
        "code": "AUS",
        "country": "Austria",
        "founded": null,
        "national": false,
        "logo": "https://media.api-sports.io/football/teams/17208.png",
        "venue_id": 3791
    },
    {
        "id": 19309,
        "name": "Austria Klagenfurt II",
        "code": null,
        "country": "Austria",
        "founded": null,
        "national": false,
        "logo": "https://media.api-sports.io/football/teams/19309.png",
        "venue_id": 22506
    },
    {
        "id": 21723,
        "name": "Donau Klagenfurt",
        "code": null,
        "country": "Austria",
        "founded": null,
        "national": false,
        "logo": "https://media.api-sports.io/football/teams/21723.png",
        "venue_id": 22507
    },
    {
        "id": 24462,
        "name": "Wolfsberger AC III",
        "code": null,
        "country": "Austria",
        "founded": null,
        "national": false,
        "logo": "https://media.api-sports.io/football/teams/24462.png",
        "venue_id": 99889899899889
    },
    {
        "id": 1396,
        "name": "SC Wiener Neustadt",
        "code": "NEU",
        "country": "Austria",
        "founded": 2008,
        "national": false,
        "logo": "https://media.api-sports.io/football/teams/1396.png",
        "venue_id": 19610
    },
    {
        "id": 4982,
        "name": "Scheiblingkirchen",
        "code": null,
        "country": "Austria",
        "founded": null,
        "national": false,
        "logo": "https://media.api-sports.io/football/teams/4982.png",
        "venue_id": 3773
    },
    {
        "id": 8245,
        "name": "Admira II",
        "code": "ADM",
        "country": "Austria",
        "founded": 1905,
        "national": false,
        "logo": "https://media.api-sports.io/football/teams/8245.png",
        "venue_id": 19578
    },
    {
        "id": 8249,
        "name": "St. Pölten II",
        "code": null,
        "country": "Austria",
        "founded": null,
        "national": false,
        "logo": "https://media.api-sports.io/football/teams/8249.png",
        "venue_id": 21001
    },
    {
        "id": 8281,
        "name": "Ardagger",
        "code": null,
        "country": "Austria",
        "founded": null,
        "national": false,
        "logo": "https://media.api-sports.io/football/teams/8281.png",
        "venue_id": 5867
    },
    {
        "id": 8283,
        "name": "Kilb",
        "code": null,
        "country": "Austria",
        "founded": 1953,
        "national": false,
        "logo": "https://media.api-sports.io/football/teams/8283.png",
        "venue_id": 5869
    },
    {
        "id": 8285,
        "name": "Langenrohr",
        "code": null,
        "country": "Austria",
        "founded": null,
        "national": false,
        "logo": "https://media.api-sports.io/football/teams/8285.png",
        "venue_id": 5871
    },
    {
        "id": 8287,
        "name": "Ortmann",
        "code": null,
        "country": "Austria",
        "founded": null,
        "national": false,
        "logo": "https://media.api-sports.io/football/teams/8287.png",
        "venue_id": 5873
    },
    {
        "id": 8288,
        "name": "Retz",
        "code": "RET",
        "country": "Austria",
        "founded": null,
        "national": false,
        "logo": "https://media.api-sports.io/football/teams/8288.png",
        "venue_id": 5874
    },
    {
        "id": 8289,
        "name": "Schrems",
        "code": null,
        "country": "Austria",
        "founded": null,
        "national": false,
        "logo": "https://media.api-sports.io/football/teams/8289.png",
        "venue_id": 22510
    },
    {
        "id": 8291,
        "name": "USC Rohrbach",
        "code": null,
        "country": "Austria",
        "founded": 1932,
        "national": false,
        "logo": "https://media.api-sports.io/football/teams/8291.png",
        "venue_id": 5877
    },
    {
        "id": 8293,
        "name": "Zwettl",
        "code": null,
        "country": "Austria",
        "founded": 1947,
        "national": false,
        "logo": "https://media.api-sports.io/football/teams/8293.png",
        "venue_id": 19959
    },
    {
        "id": 14792,
        "name": "Stockerau",
        "code": null,
        "country": "Austria",
        "founded": null,
        "national": false,
        "logo": "https://media.api-sports.io/football/teams/14792.png",
        "venue_id": 10750
    },
    {
        "id": 21722,
        "name": "St. Peter",
        "code": null,
        "country": "Austria",
        "founded": null,
        "national": false,
        "logo": "https://media.api-sports.io/football/teams/21722.png",
        "venue_id": 19860
    },
    {
        "id": 24461,
        "name": "Ybbs",
        "code": null,
        "country": "Austria",
        "founded": 1929,
        "national": false,
        "logo": "https://media.api-sports.io/football/teams/24461.png",
        "venue_id": 22511
    },
    {
        "id": 4963,
        "name": "Union Edelweiß",
        "code": null,
        "country": "Austria",
        "founded": null,
        "national": false,
        "logo": "https://media.api-sports.io/football/teams/4963.png",
        "venue_id": 22513
    },
    {
        "id": 8294,
        "name": "Bad Schallerbach",
        "code": null,
        "country": "Austria",
        "founded": null,
        "national": false,
        "logo": "https://media.api-sports.io/football/teams/8294.png",
        "venue_id": 5880
    },
    {
        "id": 8296,
        "name": "Friedburg / Pöndorf",
        "code": null,
        "country": "Austria",
        "founded": null,
        "national": false,
        "logo": "https://media.api-sports.io/football/teams/8296.png",
        "venue_id": 22515
    },
    {
        "id": 8297,
        "name": "Grün Weiß Micheldorf",
        "code": null,
        "country": "Austria",
        "founded": null,
        "national": false,
        "logo": "https://media.api-sports.io/football/teams/8297.png",
        "venue_id": 21005
    },
    {
        "id": 8298,
        "name": "Mondsee",
        "code": null,
        "country": "Austria",
        "founded": null,
        "national": false,
        "logo": "https://media.api-sports.io/football/teams/8298.png",
        "venue_id": 21006
    },
    {
        "id": 8299,
        "name": "Pregarten",
        "code": null,
        "country": "Austria",
        "founded": null,
        "national": false,
        "logo": "https://media.api-sports.io/football/teams/8299.png",
        "venue_id": 20761
    },
    {
        "id": 8302,
        "name": "St. Martin i.M.",
        "code": null,
        "country": "Austria",
        "founded": null,
        "national": false,
        "logo": "https://media.api-sports.io/football/teams/8302.png",
        "venue_id": 22516
    },
    {
        "id": 8303,
        "name": "St. Valentin",
        "code": null,
        "country": "Austria",
        "founded": null,
        "national": false,
        "logo": "https://media.api-sports.io/football/teams/8303.png",
        "venue_id": 5888
    },
    {
        "id": 8304,
        "name": "Union Perg",
        "code": null,
        "country": "Austria",
        "founded": 1962,
        "national": false,
        "logo": "https://media.api-sports.io/football/teams/8304.png",
        "venue_id": 22517
    },
    {
        "id": 8305,
        "name": "Weißkirchen / Allhaming",
        "code": null,
        "country": "Austria",
        "founded": null,
        "national": false,
        "logo": "https://media.api-sports.io/football/teams/8305.png",
        "venue_id": 5890
    },
    {
        "id": 19191,
        "name": "Bad Ischl",
        "code": null,
        "country": "Austria",
        "founded": null,
        "national": false,
        "logo": "https://media.api-sports.io/football/teams/19191.png",
        "venue_id": 5891
    },
    {
        "id": 19192,
        "name": "Ostermiething",
        "code": null,
        "country": "Austria",
        "founded": null,
        "national": false,
        "logo": "https://media.api-sports.io/football/teams/19192.png",
        "venue_id": 19866
    },
    {
        "id": 21728,
        "name": "Vortuna Bad Leonfelden",
        "code": null,
        "country": "Austria",
        "founded": null,
        "national": false,
        "logo": "https://media.api-sports.io/football/teams/21728.png",
        "venue_id": 21007
    },
    {
        "id": 24465,
        "name": "Gmunden",
        "code": null,
        "country": "Austria",
        "founded": null,
        "national": false,
        "logo": "https://media.api-sports.io/football/teams/24465.png",
        "venue_id": 21008
    },
    {
        "id": 24466,
        "name": "Union Rohrbach Berg",
        "code": null,
        "country": "Austria",
        "founded": 1932,
        "national": false,
        "logo": "https://media.api-sports.io/football/teams/24466.png",
        "venue_id": 5877
    },
    {
        "id": 4958,
        "name": "Seekirchen",
        "code": "SEE",
        "country": "Austria",
        "founded": 1945,
        "national": false,
        "logo": "https://media.api-sports.io/football/teams/4958.png",
        "venue_id": 3750
    },
    {
        "id": 4974,
        "name": "Grödig",
        "code": "GRO",
        "country": "Austria",
        "founded": 1948,
        "national": false,
        "logo": "https://media.api-sports.io/football/teams/4974.png",
        "venue_id": 22520
    },
    {
        "id": 4985,
        "name": "Straßwalchen",
        "code": null,
        "country": "Austria",
        "founded": null,
        "national": false,
        "logo": "https://media.api-sports.io/football/teams/4985.png",
        "venue_id": 3776
    },
    {
        "id": 8309,
        "name": "Bramberg",
        "code": null,
        "country": "Austria",
        "founded": null,
        "national": false,
        "logo": "https://media.api-sports.io/football/teams/8309.png",
        "venue_id": 18613
    },
    {
        "id": 8310,
        "name": "Bürmoos",
        "code": null,
        "country": "Austria",
        "founded": null,
        "national": false,
        "logo": "https://media.api-sports.io/football/teams/8310.png",
        "venue_id": 5895
    },
    {
        "id": 8311,
        "name": "Eugendorf",
        "code": "EUG",
        "country": "Austria",
        "founded": null,
        "national": false,
        "logo": "https://media.api-sports.io/football/teams/8311.png",
        "venue_id": 5896
    },
    {
        "id": 8312,
        "name": "Golling",
        "code": null,
        "country": "Austria",
        "founded": null,
        "national": false,
        "logo": "https://media.api-sports.io/football/teams/8312.png",
        "venue_id": 5897
    },
    {
        "id": 8313,
        "name": "Hallwang",
        "code": null,
        "country": "Austria",
        "founded": null,
        "national": false,
        "logo": "https://media.api-sports.io/football/teams/8313.png",
        "venue_id": 5898
    },
    {
        "id": 8314,
        "name": "Neumarkt",
        "code": "NEU",
        "country": "Austria",
        "founded": 1922,
        "national": false,
        "logo": "https://media.api-sports.io/football/teams/8314.png",
        "venue_id": 5899
    },
    {
        "id": 8315,
        "name": "Puch",
        "code": null,
        "country": "Austria",
        "founded": null,
        "national": false,
        "logo": "https://media.api-sports.io/football/teams/8315.png",
        "venue_id": 5900
    },
    {
        "id": 8316,
        "name": "Thalgau",
        "code": null,
        "country": "Austria",
        "founded": null,
        "national": false,
        "logo": "https://media.api-sports.io/football/teams/8316.png",
        "venue_id": 5901
    },
    {
        "id": 10164,
        "name": "Anif",
        "code": "SAL",
        "country": "Austria",
        "founded": 1933,
        "national": false,
        "logo": "https://media.api-sports.io/football/teams/10164.png",
        "venue_id": 7148
    },
    {
        "id": 11215,
        "name": "Salzburger AK",
        "code": null,
        "country": "Austria",
        "founded": null,
        "national": false,
        "logo": "https://media.api-sports.io/football/teams/11215.png",
        "venue_id": 22519
    },
    {
        "id": 15138,
        "name": "Siezenheim",
        "code": null,
        "country": "Austria",
        "founded": null,
        "national": false,
        "logo": "https://media.api-sports.io/football/teams/15138.png",
        "venue_id": 10853
    },
    {
        "id": 19189,
        "name": "ASV Salzburg",
        "code": null,
        "country": "Austria",
        "founded": null,
        "national": false,
        "logo": "https://media.api-sports.io/football/teams/19189.png",
        "venue_id": 9966655556565656
    },
    {
        "id": 19315,
        "name": "UFC Hallein",
        "code": null,
        "country": "Austria",
        "founded": 2020,
        "national": false,
        "logo": "https://media.api-sports.io/football/teams/19315.png",
        "venue_id": 10525
    },
    {
        "id": 4934,
        "name": "Allerheiligen",
        "code": "ALL",
        "country": "Austria",
        "founded": 1967,
        "national": false,
        "logo": "https://media.api-sports.io/football/teams/4934.png",
        "venue_id": 3727
    },
    {
        "id": 4946,
        "name": "Kalsdorf",
        "code": "KAL",
        "country": "Austria",
        "founded": null,
        "national": false,
        "logo": "https://media.api-sports.io/football/teams/4946.png",
        "venue_id": 3738
    },
    {
        "id": 8320,
        "name": "Fürstenfeld",
        "code": null,
        "country": "Austria",
        "founded": null,
        "national": false,
        "logo": "https://media.api-sports.io/football/teams/8320.png",
        "venue_id": 5905
    },
    {
        "id": 8323,
        "name": "Ilz",
        "code": null,
        "country": "Austria",
        "founded": null,
        "national": false,
        "logo": "https://media.api-sports.io/football/teams/8323.png",
        "venue_id": 20562
    },
    {
        "id": 8324,
        "name": "Lafnitz II",
        "code": null,
        "country": "Austria",
        "founded": null,
        "national": false,
        "logo": "https://media.api-sports.io/football/teams/8324.png",
        "venue_id": 1725
    },
    {
        "id": 8325,
        "name": "Lebring",
        "code": null,
        "country": "Austria",
        "founded": null,
        "national": false,
        "logo": "https://media.api-sports.io/football/teams/8325.png",
        "venue_id": 11962
    },
    {
        "id": 8329,
        "name": "TuS Heiligenkreuz",
        "code": null,
        "country": "Austria",
        "founded": null,
        "national": false,
        "logo": "https://media.api-sports.io/football/teams/8329.png",
        "venue_id": 5913
    },
    {
        "id": 8331,
        "name": "Union RB Weinland Gamlit",
        "code": null,
        "country": "Austria",
        "founded": null,
        "national": false,
        "logo": "https://media.api-sports.io/football/teams/8331.png",
        "venue_id": 5914
    },
    {
        "id": 11219,
        "name": "Frohnleiten",
        "code": null,
        "country": "Austria",
        "founded": null,
        "national": false,
        "logo": "https://media.api-sports.io/football/teams/11219.png",
        "venue_id": 7499
    },
    {
        "id": 18409,
        "name": "UFC Fehring",
        "code": null,
        "country": "Austria",
        "founded": null,
        "national": false,
        "logo": "https://media.api-sports.io/football/teams/18409.png",
        "venue_id": 18671
    },
    {
        "id": 19310,
        "name": "Köflach",
        "code": null,
        "country": "Austria",
        "founded": null,
        "national": false,
        "logo": "https://media.api-sports.io/football/teams/19310.png",
        "venue_id": 18672
    },
    {
        "id": 21533,
        "name": "Tillmitsch",
        "code": null,
        "country": "Austria",
        "founded": null,
        "national": false,
        "logo": "https://media.api-sports.io/football/teams/21533.png",
        "venue_id": 19994
    },
    {
        "id": 21729,
        "name": "FSC Hochegger Dächer",
        "code": null,
        "country": "Austria",
        "founded": null,
        "national": false,
        "logo": "https://media.api-sports.io/football/teams/21729.png",
        "venue_id": 20986
    },
    {
        "id": 21730,
        "name": "Schladming",
        "code": null,
        "country": "Austria",
        "founded": null,
        "national": false,
        "logo": "https://media.api-sports.io/football/teams/21730.png",
        "venue_id": 20987
    },
    {
        "id": 24454,
        "name": "Bad Waltersdorf",
        "code": null,
        "country": "Austria",
        "founded": null,
        "national": false,
        "logo": "https://media.api-sports.io/football/teams/24454.png",
        "venue_id": 4400022320
    },
    {
        "id": 24455,
        "name": "Kindberg-Mürzhofen",
        "code": null,
        "country": "Austria",
        "founded": 2014,
        "national": false,
        "logo": "https://media.api-sports.io/football/teams/24455.png",
        "venue_id": 15502323200
    },
    {
        "id": 1073,
        "name": "Wacker Innsbruck",
        "code": "WAC",
        "country": "Austria",
        "founded": 2002,
        "national": false,
        "logo": "https://media.api-sports.io/football/teams/1073.png",
        "venue_id": 152
    },
    {
        "id": 4999,
        "name": "Wörgl",
        "code": null,
        "country": "Austria",
        "founded": 1952,
        "national": false,
        "logo": "https://media.api-sports.io/football/teams/4999.png",
        "venue_id": 3789
    },
    {
        "id": 8334,
        "name": "Ebbs",
        "code": null,
        "country": "Austria",
        "founded": null,
        "national": false,
        "logo": "https://media.api-sports.io/football/teams/8334.png",
        "venue_id": 19236
    },
    {
        "id": 8335,
        "name": "Fügen",
        "code": null,
        "country": "Austria",
        "founded": null,
        "national": false,
        "logo": "https://media.api-sports.io/football/teams/8335.png",
        "venue_id": 10526
    },
    {
        "id": 8336,
        "name": "Kematen",
        "code": null,
        "country": "Austria",
        "founded": null,
        "national": false,
        "logo": "https://media.api-sports.io/football/teams/8336.png",
        "venue_id": 5919
    },
    {
        "id": 8338,
        "name": "Kundl",
        "code": null,
        "country": "Austria",
        "founded": null,
        "national": false,
        "logo": "https://media.api-sports.io/football/teams/8338.png",
        "venue_id": 5921
    },
    {
        "id": 8339,
        "name": "Mils",
        "code": null,
        "country": "Austria",
        "founded": null,
        "national": false,
        "logo": "https://media.api-sports.io/football/teams/8339.png",
        "venue_id": 5922
    },
    {
        "id": 8342,
        "name": "Silz / Mötz",
        "code": null,
        "country": "Austria",
        "founded": 1972,
        "national": false,
        "logo": "https://media.api-sports.io/football/teams/8342.png",
        "venue_id": 5925
    },
    {
        "id": 8343,
        "name": "St. Johann in Tirol",
        "code": null,
        "country": "Austria",
        "founded": null,
        "national": false,
        "logo": "https://media.api-sports.io/football/teams/8343.png",
        "venue_id": 5926
    },
    {
        "id": 8344,
        "name": "Swarovski Tirol II",
        "code": null,
        "country": "Austria",
        "founded": null,
        "national": false,
        "logo": "https://media.api-sports.io/football/teams/8344.png",
        "venue_id": 153
    },
    {
        "id": 8347,
        "name": "Volders",
        "code": null,
        "country": "Austria",
        "founded": null,
        "national": false,
        "logo": "https://media.api-sports.io/football/teams/8347.png",
        "venue_id": 5929
    },
    {
        "id": 8348,
        "name": "Völs",
        "code": null,
        "country": "Austria",
        "founded": null,
        "national": false,
        "logo": "https://media.api-sports.io/football/teams/8348.png",
        "venue_id": 5930
    },
    {
        "id": 12875,
        "name": "Telfs",
        "code": null,
        "country": "Austria",
        "founded": null,
        "national": false,
        "logo": "https://media.api-sports.io/football/teams/12875.png",
        "venue_id": 8216
    },
    {
        "id": 17203,
        "name": "Innsbrucker AC",
        "code": null,
        "country": "Austria",
        "founded": null,
        "national": false,
        "logo": "https://media.api-sports.io/football/teams/17203.png",
        "venue_id": 18666
    },
    {
        "id": 4968,
        "name": "Wolfurt",
        "code": null,
        "country": "Austria",
        "founded": null,
        "national": false,
        "logo": "https://media.api-sports.io/football/teams/4968.png",
        "venue_id": 3760
    },
    {
        "id": 4970,
        "name": "Alberschwende",
        "code": null,
        "country": "Austria",
        "founded": null,
        "national": false,
        "logo": "https://media.api-sports.io/football/teams/4970.png",
        "venue_id": 3762
    },
    {
        "id": 4973,
        "name": "Dornbirner SV",
        "code": null,
        "country": "Austria",
        "founded": null,
        "national": false,
        "logo": "https://media.api-sports.io/football/teams/4973.png",
        "venue_id": 18683
    },
    {
        "id": 4991,
        "name": "Hard",
        "code": "HAR",
        "country": "Austria",
        "founded": 1922,
        "national": false,
        "logo": "https://media.api-sports.io/football/teams/4991.png",
        "venue_id": 3782
    },
    {
        "id": 8257,
        "name": "Rot-Weiß Rankweil",
        "code": null,
        "country": "Austria",
        "founded": null,
        "national": false,
        "logo": "https://media.api-sports.io/football/teams/8257.png",
        "venue_id": 5844
    },
    {
        "id": 8350,
        "name": "Admira Dornbirn",
        "code": null,
        "country": "Austria",
        "founded": 1946,
        "national": false,
        "logo": "https://media.api-sports.io/football/teams/8350.png",
        "venue_id": 5932
    },
    {
        "id": 8354,
        "name": "Blau-Weiß Feldkirch",
        "code": null,
        "country": "Austria",
        "founded": 1945,
        "national": false,
        "logo": "https://media.api-sports.io/football/teams/8354.png",
        "venue_id": 5936
    },
    {
        "id": 8355,
        "name": "FC Egg",
        "code": null,
        "country": "Austria",
        "founded": null,
        "national": false,
        "logo": "https://media.api-sports.io/football/teams/8355.png",
        "venue_id": 5937
    },
    {
        "id": 8357,
        "name": "Göfis",
        "code": null,
        "country": "Austria",
        "founded": null,
        "national": false,
        "logo": "https://media.api-sports.io/football/teams/8357.png",
        "venue_id": 5939
    },
    {
        "id": 8359,
        "name": "Lochau",
        "code": null,
        "country": "Austria",
        "founded": 1946,
        "national": false,
        "logo": "https://media.api-sports.io/football/teams/8359.png",
        "venue_id": 5941
    },
    {
        "id": 8360,
        "name": "Ludesch",
        "code": null,
        "country": "Austria",
        "founded": null,
        "national": false,
        "logo": "https://media.api-sports.io/football/teams/8360.png",
        "venue_id": 5942
    },
    {
        "id": 8361,
        "name": "Lustenau",
        "code": null,
        "country": "Austria",
        "founded": 1907,
        "national": false,
        "logo": "https://media.api-sports.io/football/teams/8361.png",
        "venue_id": 5943
    },
    {
        "id": 8362,
        "name": "Nenzing",
        "code": null,
        "country": "Austria",
        "founded": null,
        "national": false,
        "logo": "https://media.api-sports.io/football/teams/8362.png",
        "venue_id": 5944
    },
    {
        "id": 15137,
        "name": "Rotenberg",
        "code": null,
        "country": "Austria",
        "founded": 2020,
        "national": false,
        "logo": "https://media.api-sports.io/football/teams/15137.png",
        "venue_id": 3742
    },
    {
        "id": 4971,
        "name": "Austria XIII",
        "code": null,
        "country": "Austria",
        "founded": 1913,
        "national": false,
        "logo": "https://media.api-sports.io/football/teams/4971.png",
        "venue_id": 3763
    },
    {
        "id": 4984,
        "name": "Stadlau",
        "code": null,
        "country": "Austria",
        "founded": null,
        "national": false,
        "logo": "https://media.api-sports.io/football/teams/4984.png",
        "venue_id": 3775
    },
    {
        "id": 5008,
        "name": "Wienerberg",
        "code": null,
        "country": "Austria",
        "founded": 1921,
        "national": false,
        "logo": "https://media.api-sports.io/football/teams/5008.png",
        "venue_id": 20999
    },
    {
        "id": 8248,
        "name": "Schwechat",
        "code": "SCH",
        "country": "Austria",
        "founded": 1899,
        "national": false,
        "logo": "https://media.api-sports.io/football/teams/8248.png",
        "venue_id": 3745
    },
    {
        "id": 8368,
        "name": "Gerasdorf Stammersdorf",
        "code": null,
        "country": "Austria",
        "founded": null,
        "national": false,
        "logo": "https://media.api-sports.io/football/teams/8368.png",
        "venue_id": 5950
    },
    {
        "id": 8369,
        "name": "Mannswörth",
        "code": null,
        "country": "Austria",
        "founded": null,
        "national": false,
        "logo": "https://media.api-sports.io/football/teams/8369.png",
        "venue_id": 5951
    },
    {
        "id": 8371,
        "name": "Slovan HAC",
        "code": null,
        "country": "Austria",
        "founded": null,
        "national": false,
        "logo": "https://media.api-sports.io/football/teams/8371.png",
        "venue_id": 5953
    },
    {
        "id": 8373,
        "name": "Vorwärts Brigittenau",
        "code": null,
        "country": "Austria",
        "founded": null,
        "national": false,
        "logo": "https://media.api-sports.io/football/teams/8373.png",
        "venue_id": 5955
    },
    {
        "id": 11201,
        "name": "Red Star Penzing",
        "code": null,
        "country": "Austria",
        "founded": 1903,
        "national": false,
        "logo": "https://media.api-sports.io/football/teams/11201.png",
        "venue_id": 21000
    },
    {
        "id": 11223,
        "name": "Hellas Kagran",
        "code": null,
        "country": "Austria",
        "founded": 1926,
        "national": false,
        "logo": "https://media.api-sports.io/football/teams/11223.png",
        "venue_id": 19962
    },
    {
        "id": 11229,
        "name": "Simmeringer SC",
        "code": null,
        "country": "Austria",
        "founded": null,
        "national": false,
        "logo": "https://media.api-sports.io/football/teams/11229.png",
        "venue_id": 7506
    },
    {
        "id": 17001,
        "name": "1980 Wien",
        "code": null,
        "country": "Austria",
        "founded": null,
        "national": false,
        "logo": "https://media.api-sports.io/football/teams/17001.png",
        "venue_id": 19475
    },
    {
        "id": 17304,
        "name": "Dinamo Helfort",
        "code": null,
        "country": "Austria",
        "founded": null,
        "national": false,
        "logo": "https://media.api-sports.io/football/teams/17304.png",
        "venue_id": 12127
    },
    {
        "id": 24459,
        "name": "First Vienna II",
        "code": null,
        "country": "Austria",
        "founded": null,
        "national": false,
        "logo": "https://media.api-sports.io/football/teams/24459.png",
        "venue_id": 18684
    },
    {
        "id": 24460,
        "name": "LAC-Inter",
        "code": null,
        "country": "Austria",
        "founded": null,
        "national": false,
        "logo": "https://media.api-sports.io/football/teams/24460.png",
        "venue_id": 22527
    }
]