[
    {
        "id": 3170,
        "name": "Diables Noirs",
        "code": null,
        "country": "Congo",
        "founded": 1950,
        "national": false,
        "logo": "3170.png",
        "venue_id": 390
    },
    {
        "id": 6428,
        "name": "Otôho d'Oyo",
        "code": null,
        "country": "Congo",
        "founded": null,
        "national": false,
        "logo": "6428.png",
        "venue_id": 4738
    },
    {
        "id": 8077,
        "name": "Étoile du Congo",
        "code": null,
        "country": "Congo",
        "founded": null,
        "national": false,
        "logo": "8077.png",
        "venue_id": 390
    },
    {
        "id": 8082,
        "name": "CARA Brazzaville",
        "code": null,
        "country": "Congo",
        "founded": 1935,
        "national": false,
        "logo": "8082.png",
        "venue_id": 390
    },
    {
        "id": 8105,
        "name": "Léopards de Dolisié",
        "code": "LEO",
        "country": "Congo",
        "founded": 1954,
        "national": false,
        "logo": "8105.png",
        "venue_id": 19300
    },
    {
        "id": 10659,
        "name": "Cheminots",
        "code": null,
        "country": "Congo",
        "founded": null,
        "national": false,
        "logo": "10659.png",
        "venue_id": 5748
    },
    {
        "id": 11679,
        "name": "Racine",
        "code": null,
        "country": "Congo",
        "founded": null,
        "national": false,
        "logo": "11679.svg",
        "venue_id": 779893375202
    },
    {
        "id": 16791,
        "name": "Inter Club",
        "code": null,
        "country": "Congo",
        "founded": null,
        "national": false,
        "logo": "16791.png",
        "venue_id": 390
    },
    {
        "id": 16792,
        "name": "JS Talangaï",
        "code": "ALA",
        "country": "Congo",
        "founded": null,
        "national": false,
        "logo": "16792.png",
        "venue_id": 390
    },
    {
        "id": 16793,
        "name": "Kondzo",
        "code": null,
        "country": "Congo",
        "founded": null,
        "national": false,
        "logo": "16793.png",
        "venue_id": 390
    },
    {
        "id": 16794,
        "name": "Nathaly's",
        "code": null,
        "country": "Congo",
        "founded": null,
        "national": false,
        "logo": "16794.png",
        "venue_id": 5748
    },
    {
        "id": 16795,
        "name": "Nico-Nicoyé",
        "code": null,
        "country": "Congo",
        "founded": null,
        "national": false,
        "logo": "16795.png",
        "venue_id": 5748
    },
    {
        "id": 16796,
        "name": "Patronage Sainte-Anne",
        "code": null,
        "country": "Congo",
        "founded": null,
        "national": false,
        "logo": "16796.png",
        "venue_id": 390
    },
    {
        "id": 16798,
        "name": "V.Club Mokanda",
        "code": null,
        "country": "Congo",
        "founded": null,
        "national": false,
        "logo": "16798.png",
        "venue_id": 5748
    },
    {
        "id": 18188,
        "name": "Nouvelle Génération",
        "code": null,
        "country": "Congo",
        "founded": null,
        "national": false,
        "logo": "18188.png",
        "venue_id": 390
    },
    {
        "id": 20462,
        "name": "Jeunesse Unie de Kintélé",
        "code": null,
        "country": "Congo",
        "founded": null,
        "national": false,
        "logo": "20462.png",
        "venue_id": 390
    },
    {
        "id": 25705,
        "name": "ACJM de Pointe-Noire",
        "code": null,
        "country": "Congo",
        "founded": 2021,
        "national": false,
        "logo": "25705.svg",
        "venue_id": 710314593742
    },
    {
        "id": 25706,
        "name": "Club Des Jeunes",
        "code": null,
        "country": "Congo",
        "founded": null,
        "national": false,
        "logo": "25706.svg",
        "venue_id": 779893375202
    },
    {
        "id": 25707,
        "name": "Inter Club Pointe Noire",
        "code": null,
        "country": "Congo",
        "founded": null,
        "national": false,
        "logo": "25707.png",
        "venue_id": 697286555125
    },
    {
        "id": 25708,
        "name": "JS Poto-Poto",
        "code": null,
        "country": "Congo",
        "founded": null,
        "national": false,
        "logo": "25708.png",
        "venue_id": 779893375202
    },
    {
        "id": 25709,
        "name": "KFA",
        "code": null,
        "country": "Congo",
        "founded": null,
        "national": false,
        "logo": "25709.svg",
        "venue_id": 339922119686
    },
    {
        "id": 25710,
        "name": "Ponténégrine",
        "code": null,
        "country": "Congo",
        "founded": null,
        "national": false,
        "logo": "25710.png",
        "venue_id": 5748
    },
    {
        "id": 25711,
        "name": "RCST Dolisié",
        "code": null,
        "country": "Congo",
        "founded": null,
        "national": false,
        "logo": "25711.png",
        "venue_id": 639273896352
    },
    {
        "id": 25712,
        "name": "St-Michel Madingou",
        "code": null,
        "country": "Congo",
        "founded": null,
        "national": false,
        "logo": "25712.png",
        "venue_id": 296446630394
    },
    {
        "id": 25732,
        "name": "Avenir",
        "code": null,
        "country": "Congo",
        "founded": null,
        "national": false,
        "logo": "25732.svg",
        "venue_id": 697286555125
    },
    {
        "id": 25823,
        "name": "AS Penarol",
        "code": null,
        "country": "Congo",
        "founded": null,
        "national": true,
        "logo": "25823.svg",
        "venue_id": 779893375202
    }
]