[
  {
    "crest": "ukraine-shakhtar",
    "name": "Shakhtar Donetsk",
    "city": "Donetsk",
    "stadium": "Donbas Arena",
    "country": "Ukraine",
    "latitude": 48.0210,
    "longitude": 37.8100,
    "capacity": 52187,
    "tier": "professional"
  },
  {
    "crest": "ukraine-dynamo",
    "name": "Dynamo Kyiv",
    "city": "Kyiv",
    "stadium": "NSC Olimpiyskiy",
    "country": "Ukraine",
    "latitude": 50.4334,
    "longitude": 30.5219,
    "capacity": 70050,
    "tier": "professional"
  },
  {
    "crest": "ukraine-lnz",
    "name": "LNZ Cherkasy",
    "city": "Cherkasy",
    "stadium": "Cherkasy Arena",
    "country": "Ukraine",
    "latitude": 49.43611045591897,
    "longitude": 32.054682955126985,
    "capacity": 10321,
    "tier": "professional"
  },
  {
    "crest": "ukraine-polissya",
    "name": "Polissya Zhytomyr",
    "city": "Zhytomyr",
    "stadium": "Tsentralnyi Stadion",
    "country": "Ukraine",
    "latitude": 49.243466114111335,
    "longitude": 28.490060412790164,
    "capacity": 5928,
    "tier": "professional"
  },
  {
    "crest": "ukraine-kryvbas",
    "name": "Kryvbas Kryvyi Rih",
    "city": "Kryvyi Rih",
    "stadium": "Metalurh Stadium",
    "country": "Ukraine",
    "latitude": 47.85959973558866,
    "longitude": 35.096942166697445,
    "capacity": 29734,
    "tier": "professional"
  },
  {
    "crest": "ukraine-metalist1925",
    "name": "Metalist 1925 Kharkiv",
    "city": "Kharkiv",
    "stadium": "OSC Metalist",
    "country": "Ukraine",
    "latitude": 49.9808,
    "longitude": 36.2617,
    "capacity": 40003,
    "tier": "professional"
  },
  {
    "crest": "ukraine-zorya",
    "name": "Zorya Luhansk",
    "city": "Luhansk",
    "stadium": "Avanhard Stadium",
    "country": "Ukraine",
    "latitude": 48.62356808099541,
    "longitude": 22.276416787630005,
    "capacity": 22288,
    "tier": "professional"
  },
  {
    "crest": "ukraine-karpaty",
    "name": "Karpaty Lviv",
    "city": "Lviv",
    "stadium": "Ukraina Stadium",
    "country": "Ukraine",
    "latitude": 49.81938687210679,
    "longitude": 24.047924866784612,
    "capacity": 28051,
    "tier": "professional"
  },
  {
    "crest": "ukraine-rukh",
    "name": "Rukh Lviv",
    "city": "Lviv",
    "stadium": "Arena Lviv",
    "country": "Ukraine",
    "latitude": 49.7753,
    "longitude": 24.0264,
    "capacity": 34915,
    "tier": "professional"
  },
  {
    "crest": "ukraine-kolos",
    "name": "Kolos Kovalivka",
    "city": "Kovalivka",
    "stadium": "Kolos Stadium",
    "country": "Ukraine",
    "latitude": 48.044602054185724,
    "longitude": 33.87369227040906,
    "capacity": 5050,
    "tier": "professional"
  },
  {
    "crest": "ukraine-veres",
    "name": "Veres Rivne",
    "city": "Rivne",
    "stadium": "Avanhard Stadium",
    "country": "Ukraine",
    "latitude": 50.6161,
    "longitude": 26.2408,
    "capacity": 7122,
    "tier": "professional"
  },
  {
    "crest": "ukraine-obolon",
    "name": "Obolon Kyiv",
    "city": "Kyiv",
    "stadium": "Obolon Arena",
    "country": "Ukraine",
    "latitude": 50.52716567606993,
    "longitude": 30.50751316866846,
    "capacity": 5103,
    "tier": "professional"
  },
  {
    "crest": "ukraine-kudrivka",
    "name": "FC Kudrivka",
    "city": "Kudrivka",
    "stadium": "Kudrivka Arena",
    "country": "Ukraine",
    "latitude": 50.53386695358442,
    "longitude": 30.233122613418974,
    "capacity": 500,
    "tier": "professional"
  },
  {
    "crest": "ukraine-epicentr",
    "name": "Epitsentr Kamianets-Podilskyi",
    "city": "Kamianets-Podilskyi",
    "stadium": "Tonkocheyeva Stadium",
    "country": "Ukraine",
    "latitude": 48.67615283086539,
    "longitude": 26.59304454345256,
    "capacity": 15150,
    "tier": "professional"
  },
  {
    "crest": "ukraine-oleksandriya",
    "name": "FC Oleksandriya",
    "city": "Oleksandriya",
    "stadium": "CSC Nika Stadium",
    "country": "Ukraine",
    "latitude": 48.67490960136301,
    "longitude": 33.106558870436814,
    "capacity": 7000,
    "tier": "professional"
  },
  {
    "crest": "ukraine-poltava",
    "name": "SC Poltava",
    "city": "Poltava",
    "stadium": "Lokomotyv Stadium",
    "country": "Ukraine",
    "latitude": 49.582658780286856,
    "longitude": 34.57694213978973,
    "capacity": 2500,
    "tier": "professional"
  },
  {
    "crest": "ukraine-vorskla",
    "name": "Vorskla Poltava",
    "city": "Poltava",
    "stadium": "Vorskla im. Butovskoho",
    "country": "Ukraine",
    "latitude": 49.5947,
    "longitude": 34.5492,
    "capacity": 23842,
    "tier": "professional"
  },
  {
    "crest": "ukraine-chornomorets",
    "name": "Chornomorets Odesa",
    "city": "Odesa",
    "stadium": "Chornomorets Stadium",
    "country": "Ukraine",
    "latitude": 46.480433813782916,
    "longitude": 30.755537912669396,
    "capacity": 34164,
    "tier": "professional"
  },
  {
    "crest": "ukraine-bukovyna",
    "name": "Bukovyna Chernivtsi",
    "city": "Chernivtsi",
    "stadium": "Bukovyna Stadium",
    "country": "Ukraine",
    "latitude": 48.27594240048722,
    "longitude": 25.941278868567487,
    "capacity": 12000,
    "tier": "professional"
  },
  {
    "crest": "ukraine-livyi-bereh",
    "name": "Livyi Bereh Kyiv",
    "city": "Kyiv",
    "stadium": "Arena Livyi Bereh",
    "country": "Ukraine",
    "latitude": 50.343963396476056,
    "longitude": 30.621867460410684,
    "capacity": 4700,
    "tier": "professional"
  },
  {
    "crest": "ukraine-metalist",
    "name": "Metalist Kharkiv",
    "city": "Kharkiv",
    "stadium": "OSC Metalist",
    "country": "Ukraine",
    "latitude": 49.98021354291399,
    "longitude": 36.261217199861754,
    "capacity": 40003,
    "tier": "professional"
  },
  {
    "crest": "ukraine-ahrobiznes",
    "name": "Ahrobiznes Volochysk",
    "city": "Volochysk",
    "stadium": "Yunist Stadium",
    "country": "Ukraine",
    "latitude": 49.00402259685725,
    "longitude": 33.6474248955839,
    "capacity": 2700,
    "tier": "professional"
  },
  {
    "crest": "ukraine-prykarpattia",
    "name": "Prykarpattia Ivano-Frankivsk",
    "city": "Ivano-Frankivsk",
    "stadium": "Rukh Stadium",
    "country": "Ukraine",
    "latitude": 48.90815298501944,
    "longitude": 24.69597684161115,
    "capacity": 6500,
    "tier": "professional"
  },
  {
    "crest": "ukraine-nyva-t",
    "name": "Nyva Ternopil",
    "city": "Ternopil",
    "stadium": "Miskyi Stadium",
    "country": "Ukraine",
    "latitude": 49.55338933531345,
    "longitude": 25.609605253926283,
    "capacity": 15150,
    "tier": "professional"
  },
  {
    "crest": "ukraine-inhulets",
    "name": "Inhulets Petrove",
    "city": "Petrove",
    "stadium": "Inhulets Stadium",
    "country": "Ukraine",
    "latitude": 48.34118354787264,
    "longitude": 33.265365514601754,
    "capacity": 1720,
    "tier": "professional"
  },
  {
    "crest": "ukraine-viktoriya",
    "name": "Viktoriya Sumy",
    "city": "Sumy",
    "stadium": "Yuvileinyi Stadium",
    "country": "Ukraine",
    "latitude": 48.14763106449418,
    "longitude": 38.35790122808534,
    "capacity": 25830,
    "tier": "professional"
  },
  {
    "crest": "ukraine-probiy",
    "name": "Probiy Horodenka",
    "city": "Horodenka",
    "stadium": "Probiy Arena",
    "country": "Ukraine",
    "latitude": 48.6592,
    "longitude": 25.5072,
    "capacity": 2500,
    "tier": "professional"
  },
  {
    "crest": "ukraine-metalurh",
    "name": "Metalurh Zaporizhzhia",
    "city": "Zaporizhzhia",
    "stadium": "Slavutych-Arena",
    "country": "Ukraine",
    "latitude": 47.859635728118505,
    "longitude": 35.0972318452682,
    "capacity": 11883,
    "tier": "professional"
  },
  {
    "crest": "ukraine-podillya",
    "name": "Podillya Khmelnytskyi",
    "city": "Khmelnytskyi",
    "stadium": "Podillia Stadium",
    "country": "Ukraine",
    "latitude": 49.420739794093436,
    "longitude": 26.99510102073521,
    "capacity": 6800,
    "tier": "professional"
  },
  {
    "crest": "ukraine-chernihiv",
    "name": "FC Chernihiv",
    "city": "Chernihiv",
    "stadium": "Chernihiv Arena",
    "country": "Ukraine",
    "latitude": 51.5425,
    "longitude": 31.2653,
    "capacity": 500,
    "tier": "professional"
  },
  {
    "crest": "ukraine-ucsa",
    "name": "UCSA Tarasivka",
    "city": "Tarasivka",
    "stadium": "Tarasivka Stadium",
    "country": "Ukraine",
    "latitude": 50.62432884879862,
    "longitude": 31.010691644336088,
    "capacity": 1000,
    "tier": "professional"
  },
  {
    "crest": "ukraine-mariupol",
    "name": "FSC Mariupol",
    "city": "Mariupol",
    "stadium": "Volodymyr Boiko Stadium",
    "country": "Ukraine",
    "latitude": 47.14409939826014,
    "longitude": 37.55856225687754,
    "capacity": 12680,
    "tier": "professional"
  }
]